 [
  {
  "content": "Alone we can do so little. Together we can do so much.",
  "author": "- Helen Keller -",
  "imageName": "icon_inspiration_designer"
  },
  {
  "content": "We cannot achieve more in life than what we believe in our heart of hearts we deserve to have.",
  "author": "- James R. Ball -",
  "imageName": "icon_inspiration_businessman"
  },
  {
  "content": "Don’t forget to be an inspiration gamer.",
  "author": "- Unknow -",
  "imageName": "icon_inspiration_vr_player"
  },
  {
  "content": "You will never find time for anything. If you want time you must make it.",
  "author": "- Charles Buxton -",
  "imageName": "icon_inspiration_designer"
  },
  {
  "content": "If you think your boss is stupid, remember: You wouldn't have a job if he was any smarter.",
  "author": "- John Gotti -",
  "imageName": "icon_inspiration_businessman"
  },
  {
  "content": "Stop crying, Monday will be over soon.",
  "author": "- Anonymous -",
  "imageName": "icon_inspiration_designer"
  },
  {
  "content": "Choose a job you love, and you will never have to work a day in your life.",
  "author": "- Confucius -",
  "imageName": "icon_inspiration_millenial"
  },
  {
  "content": "Work hard, stay positive, and get up early. It's the best part of the day.",
  "author": "- George Allen, Sr -",
  "imageName": "icon_inspiration_doctor"
  },
  {
  "content": "Let the beauty of what you love be what you do.",
  "author": "- Rumi -",
  "imageName": "icon_inspiration_policeman"
  },
  {
  "content": "Take more sleep as possible.",
  "author": "- Noah -",
  "imageName": "icon_inspiration_vr_player"
  }
  ]
